{
  "cli": {
    "version": ">= 16.0.0"
  },
  "build": {
    "development": {
      "developmentClient": true,
      "distribution": "internal",
      "env": {
        "APP_VARIANT": "development"
      },
      "android": {
        "buildType": "apk"
      },
      "ios": {
        "simulator": true
      }
    },
    "preview": {
      "distribution": "internal",
      "env": {
        "APP_VARIANT": "preview"
      },
      "android": {
        "buildType": "apk"
      },
      "ios": {
        "simulator": false
      }
    },
    "production": {
      "env": {
        "APP_VARIANT": "production"
      },
      "android": {
        "buildType": "app-bundle"
      },
      "ios": {
        "autoIncrement": "buildNumber"
      }
    }
  },
  "submit": {
    "production": {
      "android": {
        "track": "internal"
      },
      "ios": {}
    }
  }
}
